deeplabcut/__init__.py
deeplabcut/__main__.py
deeplabcut/cli.py
deeplabcut/inference_cfg.yaml
deeplabcut/pose_cfg.yaml
deeplabcut/reid_cfg.yaml
deeplabcut/version.py
deeplabcut/benchmark/__init__.py
deeplabcut/benchmark/__main__.py
deeplabcut/benchmark/base.py
deeplabcut/benchmark/benchmarks.py
deeplabcut/benchmark/cli.py
deeplabcut/benchmark/metrics.py
deeplabcut/benchmark/utils.py
deeplabcut/create_project/__init__.py
deeplabcut/create_project/add.py
deeplabcut/create_project/demo_data.py
deeplabcut/create_project/modelzoo.py
deeplabcut/create_project/new.py
deeplabcut/create_project/new_3d.py
deeplabcut/generate_training_dataset/__init__.py
deeplabcut/generate_training_dataset/frame_extraction.py
deeplabcut/generate_training_dataset/multiple_individuals_trainingsetmanipulation.py
deeplabcut/generate_training_dataset/trainingsetmanipulation.py
deeplabcut/gui/__init__.py
deeplabcut/gui/components.py
deeplabcut/gui/dlc_params.py
deeplabcut/gui/launch_script.py
deeplabcut/gui/style.qss
deeplabcut/gui/tracklet_toolbox.py
deeplabcut/gui/utils.py
deeplabcut/gui/widgets.py
deeplabcut/gui/window.py
deeplabcut/gui/assets/logo.png
deeplabcut/gui/assets/logo_transparent.png
deeplabcut/gui/assets/welcome.png
deeplabcut/gui/assets/icons/help.png
deeplabcut/gui/assets/icons/help2.png
deeplabcut/gui/assets/icons/new_project.png
deeplabcut/gui/assets/icons/new_project2.png
deeplabcut/gui/assets/icons/open.png
deeplabcut/gui/assets/icons/open2.png
deeplabcut/gui/media/__init__.py
deeplabcut/gui/media/dlc_1-01.png
deeplabcut/gui/media/logo.png
deeplabcut/gui/tabs/__init__.py
deeplabcut/gui/tabs/analyze_videos.py
deeplabcut/gui/tabs/create_project.py
deeplabcut/gui/tabs/create_training_dataset.py
deeplabcut/gui/tabs/create_videos.py
deeplabcut/gui/tabs/evaluate_network.py
deeplabcut/gui/tabs/extract_frames.py
deeplabcut/gui/tabs/extract_outlier_frames.py
deeplabcut/gui/tabs/label_frames.py
deeplabcut/gui/tabs/manage_project.py
deeplabcut/gui/tabs/modelzoo.py
deeplabcut-2.3.10.dist-info/AUTHORS
deeplabcut-2.3.10.dist-info/LICENSE
deeplabcut-2.3.10.dist-info/METADATA
deeplabcut-2.3.10.dist-info/NOTICE.yml
deeplabcut-2.3.10.dist-info/WHEEL
deeplabcut-2.3.10.dist-info/entry_points.txt
deeplabcut-2.3.10.dist-info/top_level.txt
deeplabcut-2.3.10.dist-info/RECORD
