Metadata-Version: 2.1
Name: deeplabcut
Version: 2.3.10
Summary: Markerless pose-estimation of user-defined features with deep learning
Home-page: https://github.com/DeepLabCut/DeepLabCut
Author: A. & M.W. Mathis Labs
Author-email: alexander@deeplabcut.org
Classifier: Programming Language :: Python :: 3
Classifier: License :: OSI Approved :: GNU Lesser General Public License v3 (LGPLv3)
Classifier: Operating System :: OS Independent
License-File: LICENSE
License-File: NOTICE.yml
License-File: AUTHORS
Requires-Dist: dlclibrary (>=0.0.6)
Requires-Dist: filterpy (>=1.4.4)
Requires-Dist: ruamel.yaml (>=0.15.0)
Requires-Dist: imgaug (>=0.4.0)
Requires-Dist: imageio-ffmpeg
Requires-Dist: numba (>=0.54)
Requires-Dist: matplotlib (!=3.7.0,!=3.7.1,<3.9,>=3.3)
Requires-Dist: networkx (>=2.6)
Requires-Dist: numpy (>=1.18.5)
Requires-Dist: pandas (!=1.5.0,>=1.0.1)
Requires-Dist: scikit-image (>=0.17)
Requires-Dist: scikit-learn (>=1.0)
Requires-Dist: scipy (>=1.9)
Requires-Dist: statsmodels (>=0.11)
Requires-Dist: torch
Requires-Dist: tqdm
Requires-Dist: pyyaml
Requires-Dist: Pillow (>=7.1)
Requires-Dist: tables (==3.8.0)
Provides-Extra: apple_mchips
Requires-Dist: tensorflow-macos (<2.13.0) ; extra == 'apple_mchips'
Requires-Dist: tensorflow-metal ; extra == 'apple_mchips'
Requires-Dist: tensorpack (>=0.11) ; extra == 'apple_mchips'
Requires-Dist: tf-slim (>=1.1.0) ; extra == 'apple_mchips'
Provides-Extra: docs
Requires-Dist: numpydoc ; extra == 'docs'
Provides-Extra: gui
Requires-Dist: pyside6 (==6.4.2) ; extra == 'gui'
Requires-Dist: qdarkstyle (==3.1) ; extra == 'gui'
Requires-Dist: napari-deeplabcut (>=0.2.1.6) ; extra == 'gui'
Provides-Extra: modelzoo
Requires-Dist: huggingface-hub ; extra == 'modelzoo'
Provides-Extra: openvino
Requires-Dist: openvino-dev (==2022.1.0) ; extra == 'openvino'
Provides-Extra: tf
Requires-Dist: tensorflow (<=2.10,>=2.0) ; extra == 'tf'
Requires-Dist: tensorpack (>=0.11) ; extra == 'tf'
Requires-Dist: tf-slim (>=1.1.0) ; extra == 'tf'
